nautobot_golden_config/__init__.py
nautobot_golden_config/api/__init__.py
nautobot_golden_config/api/serializers.py
nautobot_golden_config/api/urls.py
nautobot_golden_config/api/views.py
nautobot_golden_config/app-config-schema.json
nautobot_golden_config/choices.py
nautobot_golden_config/datasources.py
nautobot_golden_config/details.py
nautobot_golden_config/error_codes.py
nautobot_golden_config/exceptions.py
nautobot_golden_config/filter_extensions.py
nautobot_golden_config/filters.py
nautobot_golden_config/forms.py
nautobot_golden_config/jobs.py
nautobot_golden_config/management/commands/generate_gc_test_data.py
nautobot_golden_config/metrics.py
nautobot_golden_config/migrations/0001_initial.py
nautobot_golden_config/migrations/0002_custom_data.py
nautobot_golden_config/migrations/0003_auto_20210510_2356.py
nautobot_golden_config/migrations/0004_auto_20210616_2234.py
nautobot_golden_config/migrations/0005_json_compliance_rule.py
nautobot_golden_config/migrations/0006_multi_repo_support_temp_field.py
nautobot_golden_config/migrations/0007_multi_repo_support_convert_many.py
nautobot_golden_config/migrations/0008_multi_repo_support_final.py
nautobot_golden_config/migrations/0009_multiple_gc_settings_part_1.py
nautobot_golden_config/migrations/0010_multiple_gc_settings_part_2.py
nautobot_golden_config/migrations/0011_multiple_gc_settings_part_3.py
nautobot_golden_config/migrations/0012_multiple_gc_settings_part_4.py
nautobot_golden_config/migrations/0013_multiple_gc_settings_part_5.py
nautobot_golden_config/migrations/0014_convert_sotagg_queries_part1.py
nautobot_golden_config/migrations/0015_convert_sotagg_queries_part2.py
nautobot_golden_config/migrations/0016_convert_sotagg_queries_part3.py
nautobot_golden_config/migrations/0017_convert_sotagg_queries_part4.py
nautobot_golden_config/migrations/0018_convert_sotagg_queries_part5.py
nautobot_golden_config/migrations/0019_convert_dynamicgroup_part_1.py
nautobot_golden_config-3.0.0.dist-info/LICENSE
nautobot_golden_config-3.0.0.dist-info/METADATA
nautobot_golden_config-3.0.0.dist-info/WHEEL
nautobot_golden_config-3.0.0.dist-info/RECORD
