Metadata-Version: 2.3
Name: nautobot-golden-config
Version: 3.0.0
Summary: An app for configuration on nautobot
License: Apache-2.0
Keywords: nautobot,nautobot-app,nautobot-plugin
Author: Network to Code, LLC
Author-email: opensource@networktocode.com
Requires-Python: >=3.10,<3.14
Classifier: Development Status :: 5 - Production/Stable
Classifier: Intended Audience :: Developers
Classifier: License :: OSI Approved :: Apache Software License
Classifier: Programming Language :: Python :: 3
Classifier: Programming Language :: Python :: 3.10
Classifier: Programming Language :: Python :: 3.11
Classifier: Programming Language :: Python :: 3.12
Classifier: Programming Language :: Python :: 3.13
Provides-Extra: all
Requires-Dist: deepdiff (>=8.6.1,<9.0.0)
Requires-Dist: django-pivot (>=1.9.0,<1.10.0)
Requires-Dist: hier-config (>=3.2.2,<4.0.0)
Requires-Dist: nautobot (>=3.0.0,<4.0.0)
Requires-Dist: nautobot-capacity-metrics (>=4.0.0,<5.0.0)
Requires-Dist: nautobot-plugin-nornir (>=3.0.0,<4.0.0)
Requires-Dist: netutils (>=1.5.0,<2.0.0)
Requires-Dist: toml (>=0.10.2,<0.11.0)
Requires-Dist: xmldiff (>=2.6.3,<3.0.0)
Project-URL: Bug Tracker, https://github.com/nautobot/nautobot-app-golden-config/issues
Project-URL: Changelog, https://docs.nautobot.com/projects/golden-config/en/latest/admin/release_notes/
Project-URL: Documentation, https://docs.nautobot.com/projects/golden-config/en/latest/
Project-URL: Homepage, https://github.com/nautobot/nautobot-app-golden-config
Project-URL: Repository, https://github.com/nautobot/nautobot-app-golden-config
